{"filename": "contracts\\vulnerable\\sb_access_c_incorrect_constructor_name1.sol", "label": "access_control", "vuln_type": "access_control", "method": "rich_regex_v3", "num_nodes": 6, "num_edges": 5, "nodes": [{"id": 0, "type": "ContractDefinition", "name": "Missing", "features": [0.0, 0.0, 1.0, 0.0, 1.0, 1.0, 0.13403887713484575, 0.0, 0.0, 0.0, 1.0, 0.0, 1.0, 0.0, 0.04986220775524182, 0.060878364828887435]}, {"id": 1, "type": "StateVariable", "name": "owner", "features": [0.16432813730423526, 0.0, 0.0, 0.0, 0.0, 0.0, 0.15391362240176795, 0.0, 0.0, 0.0, 0.0, 0.0, 0.0, 0.0, 0.0, 0.043174074006299315]}, {"id": 2, "type": "FunctionDefinition", "name": "IamMissing", "features": [0.013535655123582166, 0.0, 0.0, 0.0, 1.0, 1.0, 0.18376247045394417, 0.0, 0.0, 0.0, 0.0, 0.0, 0.0, 0.0, 0.0, 0.0]}, {"id": 3, "type": "FunctionDefinition", "name": "withdraw", "features": [0.14899236384622208, 0.0, 0.0, 0.0, 0.0, 1.0, 0.2616036603309525, 0.0, 0.0, 0.0, 1.0, 0.0, 0.0, 0.0, 0.01717446724646682, 0.0]}, {"id": 4, "type": "TransferCall", "name": "TransferCall", "features": [0.48507383168694357, 0.0, 1.0, 0.0, 0.0, 1.0, 0.4323334285935554, 0.0, 0.0, 0.0, 1.0, 0.0, 0.0, 0.0, 0.07868053005414817, 0.025629208428738188]}, {"id": 5, "type": "ModifierDefinition", "name": "onlyowner", "features": [0.10953084289648851, 0.0, 1.0, 0.0, 1.0, 1.0, 0.18628829405651542, 0.0, 0.0, 0.0, 1.0, 0.0, 1.0, 0.0, 0.050095928273792514, 0.0]}], "edges": [{"src": 0, "dst": 1, "type": "AST_CHILD"}, {"src": 0, "dst": 2, "type": "AST_CHILD"}, {"src": 0, "dst": 3, "type": "AST_CHILD"}, {"src": 3, "dst": 4, "type": "CALL_DEP"}, {"src": 0, "dst": 5, "type": "AST_CHILD"}], "graph_features": [0.0, 0.10543457743935827, 0.0, 0.0, 0.09377454020467733, 0.0, 0.05260881018579527, 0.09596208583126024, 0.0, 0.0], "augmented": true, "aug_id": 3}