{"filename": "contracts\\vulnerable\\sb_access_c_arbitrary_location_write_simple.sol", "label": "access_control", "vuln_type": "access_control", "method": "rich_regex_v3", "num_nodes": 10, "num_edges": 9, "nodes": [{"id": 0, "type": "ContractDefinition", "name": "Wallet", "features": [0.0, 0.0, 0.0, 0.0, 1.0, 1.0, 0.02328044715671121, 0.0, 0.0, 0.0, 1.0, 0.0, 1.0, 0.0, 0.08908921569217841, 0.14875647870512676]}, {"id": 1, "type": "StateVariable", "name": "owner", "features": [0.14918654724988561, 0.0, 0.0, 0.0, 0.0, 0.0, 0.14237242167380554, 0.0, 1.0, 0.0, 0.0, 0.0, 0.0, 0.0, 0.08080334252761802, 0.07836469427784772]}, {"id": 2, "type": "FunctionDefinition", "name": "PushBonusCode", "features": [0.08308682532793238, 0.0, 0.0, 0.0, 0.0, 1.0, 0.12373860026893248, 0.0, 0.0, 0.0, 0.0, 0.0, 0.0, 0.0, 0.0, 0.09564623688441658]}, {"id": 3, "type": "FunctionDefinition", "name": "PopBonusCode", "features": [0.0, 0.0, 0.0, 0.0, 0.0, 1.0, 0.1559620495266005, 0.0, 0.0, 0.0, 1.0, 0.0, 0.0, 0.0, 0.0, 0.0]}, {"id": 4, "type": "RequireStatement", "name": "require", "features": [0.5443449290204786, 0.0, 0.0, 0.0, 0.0, 1.0, 0.401064130472723, 0.0, 0.0, 0.0, 1.0, 0.0, 0.0, 0.0, 0.0, 0.0]}, {"id": 5, "type": "FunctionDefinition", "name": "UpdateBonusCodeAt", "features": [0.0, 0.0, 0.0, 0.0, 0.0, 1.0, 0.24227916036997688, 0.0, 0.0, 0.0, 1.0, 0.0, 0.0, 0.0, 0.0, 0.10802495554309613]}, {"id": 6, "type": "RequireStatement", "name": "require", "features": [0.5734667941896482, 0.0, 0.0, 0.0, 0.0, 1.0, 0.33266014382593456, 0.0, 0.0, 0.0, 1.0, 0.0, 0.0, 0.0, 0.0, 0.07696962082310309]}, {"id": 7, "type": "FunctionDefinition", "name": "Destroy", "features": [0.0, 0.0, 0.0, 0.0, 1.0, 1.0, 0.2728958044915018, 0.0, 0.0, 0.0, 1.0, 0.0, 0.0, 0.0, 0.06446704654607063, 0.0]}, {"id": 8, "type": "RequireStatement", "name": "require", "features": [0.46901567465917554, 0.0, 0.0, 0.0, 1.0, 1.0, 0.32043713767335685, 0.0, 1.0, 0.0, 1.0, 0.0, 0.0, 0.0, 0.021180684881199764, 0.0]}, {"id": 9, "type": "Constructor", "name": "constructor", "features": [0.8647005653869788, 0.0, 0.0, 0.0, 1.0, 1.0, 0.17405352929684426, 0.0, 0.0, 0.0, 0.0, 0.0, 0.0, 0.0, 0.0, 0.0]}], "edges": [{"src": 0, "dst": 1, "type": "AST_CHILD"}, {"src": 0, "dst": 2, "type": "AST_CHILD"}, {"src": 0, "dst": 3, "type": "AST_CHILD"}, {"src": 3, "dst": 4, "type": "AST_CHILD"}, {"src": 0, "dst": 5, "type": "AST_CHILD"}, {"src": 5, "dst": 6, "type": "AST_CHILD"}, {"src": 0, "dst": 7, "type": "AST_CHILD"}, {"src": 7, "dst": 8, "type": "AST_CHILD"}, {"src": 0, "dst": 9, "type": "AST_CHILD"}], "graph_features": [0.008857394221552177, 0.10336822589327076, 0.0, 0.002421270005873333, 0.14019989066114613, 0.0029744038735639478, 0.12802171899112788, 0.1043090539010494, 0.00028536424784955037, 0.0], "augmented": true, "aug_id": 4}