{"filename": "contracts\\vulnerable\\sb_time_man_governmental_survey.sol", "label": "logic_error", "vuln_type": "logic_error", "method": "rich_regex_v3", "num_nodes": 16, "num_edges": 22, "nodes": [{"id": 0, "type": "ContractDefinition", "name": "Governmental", "features": [0.018125593555897348, 0.0, 1.0, 0.0, 1.0, 1.0, 0.0, 0.0, 1.0, 0.0, 0.0, 0.0, 0.0, 0.0, 0.09008389421426011, 0.08019856394266033]}, {"id": 1, "type": "StateVariable", "name": "owner", "features": [0.17987938066563114, 0.0, 0.0, 0.0, 0.0, 1.0, 0.14755027874217697, 0.0, 0.0, 0.0, 0.0, 0.0, 0.0, 0.0, 0.0, 0.0]}, {"id": 2, "type": "StateVariable", "name": "lastInvestor", "features": [0.21331838708863052, 0.0, 0.0, 0.0, 0.0, 1.0, 0.20051590020676116, 0.0, 0.0, 0.0, 0.0, 0.0, 0.0, 0.0, 0.019768526991901517, 0.053655629049618896]}, {"id": 3, "type": "StateVariable", "name": "jackpot", "features": [0.19041206208819872, 0.0, 0.0, 0.0, 1.0, 1.0, 0.22916775449520327, 0.0, 0.0, 0.0, 0.0, 0.0, 0.0, 0.0, 0.08987783788021658, 0.03787934658501554]}, {"id": 4, "type": "StateVariable", "name": "lastInvestmentTimestamp", "features": [0.17744801455851203, 0.0, 0.0, 0.0, 0.0, 1.0, 0.228140847283428, 0.0, 0.0, 0.0, 0.0, 0.0, 0.0, 0.0, 0.0, 0.044043552785012444]}, {"id": 5, "type": "StateVariable", "name": "ONE_MINUTE", "features": [0.11536938899791144, 0.0, 0.0, 0.0, 1.0, 1.0, 0.25418238427328677, 0.0, 0.0, 0.0, 0.0, 0.0, 0.0, 0.0, 0.0, 0.0060763159207475066]}, {"id": 6, "type": "FunctionDefinition", "name": "Governmental", "features": [0.012873602619345514, 0.0, 0.0, 0.0, 1.0, 0.0, 0.18462061623610945, 0.0, 0.0, 0.0, 0.0, 0.0, 0.0, 0.0, 0.08830339459292712, 0.0]}, {"id": 7, "type": "IfStatement", "name": "if", "features": [0.2847123628354317, 0.0, 0.0, 0.0, 1.0, 0.0, 0.4707435575051764, 0.0, 0.0, 0.0, 0.0, 0.0, 0.0, 0.0, 0.005082067884728594, 0.0032259375327853106]}, {"id": 8, "type": "FunctionDefinition", "name": "invest", "features": [0.002603989780893802, 0.0, 0.0, 0.0, 1.0, 0.0, 0.17021614421410203, 0.0, 1.0, 0.0, 0.0, 0.0, 0.0, 0.0, 0.0, 0.0]}, {"id": 9, "type": "ArithmeticOp", "name": "arithmetic", "features": [0.6905971752769046, 0.0, 0.0, 1.0, 1.0, 0.0, 0.3860219811516881, 0.0, 1.0, 0.0, 0.0, 0.0, 0.0, 0.0, 0.0, 0.0]}, {"id": 10, "type": "IfStatement", "name": "if", "features": [0.3379065894505682, 0.0, 0.0, 0.0, 1.0, 0.0, 0.3721728007858663, 0.0, 1.0, 0.0, 0.0, 0.0, 0.0, 0.0, 0.0, 0.0]}, {"id": 11, "type": "FunctionDefinition", "name": "resetInvestment", "features": [0.0016524602141121739, 0.0, 1.0, 0.0, 1.0, 0.0, 0.19704625874503157, 1.0, 0.0, 0.0, 0.0, 0.0, 0.0, 0.0, 0.004131809669985886, 0.06755707686766971]}, {"id": 12, "type": "SendCall", "name": "SendCall", "features": [0.5464941983587713, 0.0, 1.0, 0.0, 1.0, 0.0, 0.4977665906071219, 1.0, 0.0, 0.0, 0.0, 0.0, 0.0, 0.0, 0.03776007263286476, 0.03919631535875119]}, {"id": 13, "type": "IfStatement", "name": "if", "features": [0.25602914197058785, 0.0, 1.0, 0.0, 1.0, 0.0, 0.3944192960643737, 1.0, 0.0, 0.0, 0.0, 0.0, 0.0, 0.0, 0.05387703176768974, 0.0]}, {"id": 14, "type": "FunctionDefinition", "name": "attack", "features": [0.0, 0.0, 0.0, 0.0, 0.0, 0.0, 0.1948148015876688, 0.0, 0.0, 0.0, 0.0, 0.0, 0.0, 0.0, 0.04361312016430513, 0.059566186321254086]}, {"id": 15, "type": "IfStatement", "name": "if", "features": [0.0, 0.0, 0.0, 0.0, 0.0, 0.0, 0.2795221471598557, 0.0, 0.0, 0.0, 0.0, 0.0, 0.0, 0.0, 0.0, 0.0]}], "edges": [{"src": 0, "dst": 1, "type": "AST_CHILD"}, {"src": 0, "dst": 2, "type": "AST_CHILD"}, {"src": 0, "dst": 3, "type": "AST_CHILD"}, {"src": 0, "dst": 4, "type": "AST_CHILD"}, {"src": 0, "dst": 5, "type": "AST_CHILD"}, {"src": 0, "dst": 6, "type": "AST_CHILD"}, {"src": 6, "dst": 7, "type": "AST_CHILD"}, {"src": 0, "dst": 8, "type": "AST_CHILD"}, {"src": 8, "dst": 9, "type": "AST_CHILD"}, {"src": 8, "dst": 10, "type": "AST_CHILD"}, {"src": 9, "dst": 10, "type": "CFG_BRANCH"}, {"src": 0, "dst": 11, "type": "AST_CHILD"}, {"src": 12, "dst": 1, "type": "DATA_DEP"}, {"src": 12, "dst": 2, "type": "DATA_DEP"}, {"src": 12, "dst": 3, "type": "DATA_DEP"}, {"src": 12, "dst": 4, "type": "DATA_DEP"}, {"src": 12, "dst": 5, "type": "DATA_DEP"}, {"src": 11, "dst": 13, "type": "AST_CHILD"}, {"src": 12, "dst": 13, "type": "CFG_BRANCH"}, {"src": 0, "dst": 14, "type": "AST_CHILD"}, {"src": 14, "dst": 15, "type": "AST_CHILD"}], "graph_features": [0.0, 0.0, 0.02005276471754197, 0.00801923561781436, 0.0011411759521554304, 0.002317497792823903, 0.13158005686782798, 0.004352683414532644, 0.00380486709937019, 0.024504999764750093], "augmented": true, "aug_id": 0}