{"filename": "contracts\\vulnerable\\sb_unchecke_0x9d06cbafa865037a01d322d3f4222fa3e04e5488.sol", "label": "logic_error", "vuln_type": "logic_error", "method": "rich_regex_v3", "num_nodes": 20, "num_edges": 30, "nodes": [{"id": 0, "type": "ContractDefinition", "name": "Delta", "features": [0.003805173237726367, 1.0, 1.0, 0.0, 1.0, 1.0, 0.0, 0.0, 0.0, 0.0, 1.0, 0.0, 1.0, 0.0, 0.07199338296134136, 0.28310662937894804]}, {"id": 1, "type": "StateVariable", "name": "c", "features": [0.18678496641987505, 0.0, 0.0, 0.0, 1.0, 1.0, 0.0, 0.0, 0.0, 0.0, 0.0, 0.0, 0.0, 0.0, 0.0, 0.09102004457306367]}, {"id": 2, "type": "StateVariable", "name": "owner", "features": [0.1364181027607294, 0.0, 0.0, 0.0, 1.0, 1.0, 0.18926535175219428, 0.0, 0.0, 0.0, 0.0, 0.0, 0.0, 0.0, 0.0, 0.013796455123772425]}, {"id": 3, "type": "StateVariable", "name": "owner2", "features": [0.07961036588905035, 0.0, 0.0, 0.0, 1.0, 1.0, 0.24329959024834166, 0.0, 0.0, 0.0, 0.0, 0.0, 0.0, 0.0, 0.0, 0.08011724217620815]}, {"id": 4, "type": "StateVariable", "name": "active", "features": [0.0514568111773028, 0.0, 0.0, 0.0, 1.0, 1.0, 0.15193890670017432, 0.0, 0.0, 0.0, 0.0, 0.0, 1.0, 0.0, 0.05637676348551993, 0.044418183867137584]}, {"id": 5, "type": "StateVariable", "name": "token_price", "features": [0.19400411598568995, 0.0, 0.0, 0.0, 1.0, 1.0, 0.1806298470977758, 1.0, 0.0, 0.0, 0.0, 0.0, 0.0, 0.0, 0.0, 0.05282733149109463]}, {"id": 6, "type": "StateVariable", "name": "tokens_buy", "features": [0.16664679461552354, 0.0, 0.0, 0.0, 1.0, 0.0, 0.17236521233893418, 0.0, 0.0, 0.0, 0.0, 0.0, 0.0, 0.0, 0.0, 0.12025414484912371]}, {"id": 7, "type": "StateVariable", "name": "sum2", "features": [0.1709542553764159, 0.0, 0.0, 0.0, 1.0, 0.0, 0.19380254494463925, 0.0, 0.0, 0.0, 0.0, 0.0, 0.0, 0.0, 0.015351749747118774, 0.056673504335605085]}, {"id": 8, "type": "StateVariable", "name": "balance", "features": [0.1727426670514405, 0.0, 0.0, 0.0, 0.0, 0.0, 0.11157485078219381, 0.0, 0.0, 0.0, 0.0, 0.0, 1.0, 0.0, 0.0, 0.032683401548985865]}, {"id": 9, "type": "FunctionDefinition", "name": "tokens_buy", "features": [0.03687868278758405, 1.0, 1.0, 0.0, 1.0, 0.0, 0.2598647150647851, 0.0, 0.0, 0.0, 1.0, 0.0, 1.0, 0.0, 0.019105709267321105, 0.13714327678760474]}, {"id": 10, "type": "RequireStatement", "name": "require", "features": [0.0, 1.0, 1.0, 0.0, 1.0, 0.0, 0.4606402380263838, 0.0, 0.0, 1.0, 1.0, 0.0, 1.0, 0.0, 0.0, 0.1653762831606792]}, {"id": 11, "type": "ExternalCall", "name": "ExternalCall", "features": [0.2635457672124727, 1.0, 1.0, 0.0, 1.0, 0.0, 0.3544710601919909, 0.0, 0.0, 0.0, 1.0, 0.0, 1.0, 0.0, 0.08810546260109753, 0.14832873766414684]}, {"id": 12, "type": "SendCall", "name": "SendCall", "features": [0.4669770000548985, 1.0, 1.0, 0.0, 1.0, 0.0, 0.4086070632715578, 0.0, 0.0, 0.0, 1.0, 0.0, 1.0, 0.0, 0.08327604675503414, 0.11394954058454132]}, {"id": 13, "type": "IfStatement", "name": "if", "features": [0.2385971308594094, 0.0, 1.0, 0.0, 0.0, 1.0, 0.3452656151330231, 0.0, 0.0, 0.0, 1.0, 0.0, 1.0, 0.0, 0.0004993878536211013, 0.06320968944126]}, {"id": 14, "type": "FunctionDefinition", "name": "withdraw", "features": [0.020102432931501647, 0.0, 1.0, 0.0, 1.0, 0.0, 0.16239978251433046, 0.0, 0.0, 0.0, 1.0, 0.0, 0.0, 0.0, 0.08935453299875647, 0.07632751925664391]}, {"id": 15, "type": "SendCall", "name": "SendCall", "features": [0.0, 0.0, 1.0, 0.0, 1.0, 0.0, 0.36467693972732856, 0.0, 0.0, 0.0, 1.0, 0.0, 0.0, 0.0, 0.0, 0.02203291511238637]}, {"id": 16, "type": "IfStatement", "name": "if", "features": [0.2655245968508909, 0.0, 1.0, 0.0, 1.0, 0.0, 0.37163261559695093, 0.0, 0.0, 0.0, 1.0, 0.0, 0.0, 0.0, 0.1160484135421168, 0.0]}, {"id": 17, "type": "FunctionDefinition", "name": "change_token_price", "features": [0.0, 0.0, 0.0, 0.0, 1.0, 0.0, 0.19456578367908084, 0.0, 0.0, 0.0, 1.0, 0.0, 0.0, 0.0, 0.01224331633529821, 0.0]}, {"id": 18, "type": "FunctionDefinition", "name": "change_active", "features": [0.0, 0.0, 0.0, 0.0, 1.0, 0.0, 0.18372643504550457, 0.0, 0.0, 0.0, 1.0, 0.0, 0.0, 0.0, 0.0, 0.0]}, {"id": 19, "type": "ModifierDefinition", "name": "onlyOwner", "features": [0.11020769863430291, 1.0, 1.0, 0.0, 1.0, 1.0, 0.20250902072376542, 0.0, 0.0, 0.0, 1.0, 0.0, 1.0, 0.0, 0.08532754517317054, 0.14198075067256882]}], "edges": [{"src": 0, "dst": 1, "type": "AST_CHILD"}, {"src": 0, "dst": 2, "type": "AST_CHILD"}, {"src": 0, "dst": 3, "type": "AST_CHILD"}, {"src": 0, "dst": 4, "type": "AST_CHILD"}, {"src": 0, "dst": 5, "type": "AST_CHILD"}, {"src": 0, "dst": 6, "type": "AST_CHILD"}, {"src": 0, "dst": 7, "type": "AST_CHILD"}, {"src": 0, "dst": 8, "type": "AST_CHILD"}, {"src": 0, "dst": 9, "type": "AST_CHILD"}, {"src": 9, "dst": 10, "type": "AST_CHILD"}, {"src": 9, "dst": 11, "type": "CALL_DEP"}, {"src": 10, "dst": 11, "type": "CFG_NEXT"}, {"src": 9, "dst": 12, "type": "CALL_DEP"}, {"src": 11, "dst": 12, "type": "CFG_NEXT"}, {"src": 12, "dst": 1, "type": "DATA_DEP"}, {"src": 12, "dst": 2, "type": "DATA_DEP"}, {"src": 12, "dst": 4, "type": "DATA_DEP"}, {"src": 12, "dst": 5, "type": "DATA_DEP"}, {"src": 12, "dst": 6, "type": "DATA_DEP"}, {"src": 12, "dst": 7, "type": "DATA_DEP"}, {"src": 12, "dst": 13, "type": "CFG_BRANCH"}, {"src": 0, "dst": 14, "type": "AST_CHILD"}, {"src": 14, "dst": 15, "type": "CALL_DEP"}, {"src": 14, "dst": 16, "type": "AST_CHILD"}, {"src": 15, "dst": 16, "type": "CFG_BRANCH"}, {"src": 0, "dst": 17, "type": "AST_CHILD"}, {"src": 0, "dst": 18, "type": "AST_CHILD"}, {"src": 0, "dst": 19, "type": "AST_CHILD"}], "graph_features": [0.0595603712274326, 0.0, 0.0, 0.8909981622112684, 0.2700224831089312, 0.0017037980519137913, 0.14578403759394692, 0.20547551413555898, 0.0, 0.001702122249947593], "augmented": true, "aug_id": 3}